{"upload_date": "20141013", "protocol": "https", "creator": null, "format_note": "hd720", "height": 720, "thumbnail": "https://i.ytimg.com/vi/Bznxx12Ptl0/maxresdefault.jpg", "like_count": 2484222, "duration": 149, "fulltitle": "AronChupa - I'm an Albatraoz (Official Music Video)", "playlist_index": null, "view_count": 451204917, "playlist": null, "title": "AronChupa - I'm an Albatraoz (Official Music Video)", "_filename": "Bznxx12Ptl0", "tags": ["Aron Ekberg", "Dance/House/Techno", "AronChupa", "I'm an Albatraoz"], "is_live": null, "id": "Bznxx12Ptl0", "dislike_count": 96635, "average_rating": 4.85022783279, "abr": 192, "categories": ["Music"], "age_limit": 0, "annotations": null, "webpage_url_basename": "watch", "acodec": " mp4a.40.2", "display_id": "Bznxx12Ptl0", "automatic_captions": {}, "description": "Instagram: http://instagram.com/aronchupa\nFacebook: https://www.facebook.com/aronchupaofficial\niTunes: http://smarturl.it/Albatraoz\nSpotify: http://smarturl.it/AlbatraozSpot\n\nOfficial Video for AronChupa\u2019s \u201cI\u2019m an Albatraoz\u201d. Directed by Aron Ekberg and Sertac Yildizhan. Produced by Jessica Fee, Sean Graham and Patrick Heinemann. Edited by Jacob Englund. Starring and vocals by Nora Ekberg.\n\nLyrics:\nStarts off with some french dude speaking, have no clue what he is saying but it sounds cool\u2026\n\nVers 1\nLet me tell you all a story about a mouse named Lorry\nYeah, Lorry was a mouse in a big brown house\nShe called herself the hoe, with the money money flow\nBut fuck that little mouse cuz I\u2019m an Albatraoz\n\nVers 2\nYeah Lorry said she was a mouse, smoked that cheesn\u2019 like a baoz\nMonilie money money hoe, chinka chinka chingka-flow\nLorry was a witch, yeah a sneaky little bitch\nSo fuck that little mouse cuz I\u2019m an Albatraoz", "format": "22 - 1280x720 (hd720)", "start_time": null, "uploader": "AronChupaVEVO", "format_id": "22", "uploader_id": "AronChupaVEVO", "subtitles": {}, "thumbnails": [{"url": "https://i.ytimg.com/vi/Bznxx12Ptl0/maxresdefault.jpg", "id": "0"}], "alt_title": null, "url": "https://r2---sn-uxax3vhgn-cxbr.googlevideo.com/videoplayback?itag=22&gcr=rs&source=youtube&ratebypass=yes&upn=tkOWzqnIelg&initcwndbps=1202500&expire=1454924460&sver=3&key=yt6&sparams=dur%2Cgcr%2Cid%2Cinitcwndbps%2Cip%2Cipbits%2Citag%2Clmt%2Cmime%2Cmm%2Cmn%2Cms%2Cmv%2Cpcm2cms%2Cpl%2Cratebypass%2Crequiressl%2Csource%2Cupn%2Cexpire&mm=31&ip=109.92.0.167&mn=sn-uxax3vhgn-cxbr&ms=au&requiressl=yes&mt=1454902792&pl=17&mv=m&id=o-AFKb0GDhKsbyD5pke-0CCapkkZkMzXE_Ef8Jfu36_AS5&dur=148.514&mime=video%2Fmp4&ipbits=0&pcm2cms=yes&fexp=9415516%2C9416126%2C9418581%2C9419451%2C9420452%2C9422596%2C9422844%2C9422970%2C9423291%2C9423661%2C9423662%2C9425619%2C9426224%2C9426653%2C9427061%2C9427363%2C9427670&lmt=1429525764283120&signature=B2E05B810A33FBD8A43062ED33B37E05F2907F14.3D30E84B8F134E02C4C9504582CAFC8945F2D024", "extractor_key": "Youtube", "vcodec": "avc1.64001F", "http_headers": {"Accept-Charset": "ISO-8859-1,utf-8;q=0.7,*;q=0.7", "Accept-Language": "en-us,en;q=0.5", "Accept-Encoding": "gzip, deflate", "Accept": "text/html,application/xhtml+xml,application/xml;q=0.9,*/*;q=0.8", "User-Agent": "Mozilla/5.0 (X11; Linux x86_64; rv:10.0) Gecko/20150101 Firefox/20.0 (Chrome)"}, "player_url": "//s.ytimg.com/yts/jsbin/player-en_US-vfl93P520/base.js", "ext": "mp4", "extractor": "youtube", "end_time": null, "webpage_url": "https://www.youtube.com/watch?v=Bznxx12Ptl0", "formats": [{"http_headers": {"Accept-Charset": "ISO-8859-1,utf-8;q=0.7,*;q=0.7", "Accept-Language": "en-us,en;q=0.5", "Accept-Encoding": "gzip, deflate", "Accept": "text/html,application/xhtml+xml,application/xml;q=0.9,*/*;q=0.8", "User-Agent": "Mozilla/5.0 (X11; Linux x86_64; rv:10.0) Gecko/20150101 Firefox/20.0 (Chrome)"}, "tbr": 55.836, "protocol": "https", "format": "249 - audio only (DASH audio)", "url": "https://r2---sn-uxax3vhgn-cxbr.googlevideo.com/videoplayback?itag=249&gcr=rs&source=youtube&clen=991313&initcwndbps=1202500&upn=tkOWzqnIelg&expire=1454924460&sver=3&key=yt6&keepalive=yes&sparams=clen%2Cdur%2Cgcr%2Cgir%2Cid%2Cinitcwndbps%2Cip%2Cipbits%2Citag%2Ckeepalive%2Clmt%2Cmime%2Cmm%2Cmn%2Cms%2Cmv%2Cpcm2cms%2Cpl%2Crequiressl%2Csource%2Cupn%2Cexpire&mm=31&ip=109.92.0.167&mn=sn-uxax3vhgn-cxbr&ms=au&requiressl=yes&mt=1454902792&pl=17&mv=m&id=o-AFKb0GDhKsbyD5pke-0CCapkkZkMzXE_Ef8Jfu36_AS5&dur=148.461&mime=audio%2Fwebm&ipbits=0&pcm2cms=yes&gir=yes&fexp=9415516%2C9416126%2C9418581%2C9419451%2C9420452%2C9422596%2C9422844%2C9422970%2C9423291%2C9423661%2C9423662%2C9425619%2C9426224%2C9426653%2C9427061%2C9427363%2C9427670&lmt=1449553639335483&signature=C2136A468BECA92D11FD30AB8CDC0EA54EA3A178.4AA22D4C84238CE96E30E5D62DE93F6D2CA39D4B&ratebypass=yes", "filesize": 991313, "vcodec": "none", "format_note": "DASH audio", "abr": 50, "player_url": "//s.ytimg.com/yts/jsbin/player-en_US-vfl93P520/base.js", "ext": "webm", "preference": -50, "format_id": "249", "acodec": "opus"}, {"http_headers": {"Accept-Charset": "ISO-8859-1,utf-8;q=0.7,*;q=0.7", "Accept-Language": "en-us,en;q=0.5", "Accept-Encoding": "gzip, deflate", "Accept": "text/html,application/xhtml+xml,application/xml;q=0.9,*/*;q=0.8", "User-Agent": "Mozilla/5.0 (X11; Linux x86_64; rv:10.0) Gecko/20150101 Firefox/20.0 (Chrome)"}, "tbr": 77.749, "protocol": "https", "format": "250 - audio only (DASH audio)", "url": "https://r2---sn-uxax3vhgn-cxbr.googlevideo.com/videoplayback?itag=250&gcr=rs&source=youtube&clen=1349417&initcwndbps=1202500&upn=tkOWzqnIelg&expire=1454924460&sver=3&key=yt6&keepalive=yes&sparams=clen%2Cdur%2Cgcr%2Cgir%2Cid%2Cinitcwndbps%2Cip%2Cipbits%2Citag%2Ckeepalive%2Clmt%2Cmime%2Cmm%2Cmn%2Cms%2Cmv%2Cpcm2cms%2Cpl%2Crequiressl%2Csource%2Cupn%2Cexpire&mm=31&ip=109.92.0.167&mn=sn-uxax3vhgn-cxbr&ms=au&requiressl=yes&mt=1454902792&pl=17&mv=m&id=o-AFKb0GDhKsbyD5pke-0CCapkkZkMzXE_Ef8Jfu36_AS5&dur=148.461&mime=audio%2Fwebm&ipbits=0&pcm2cms=yes&gir=yes&fexp=9415516%2C9416126%2C9418581%2C9419451%2C9420452%2C9422596%2C9422844%2C9422970%2C9423291%2C9423661%2C9423662%2C9425619%2C9426224%2C9426653%2C9427061%2C9427363%2C9427670&lmt=1449553654411154&signature=C13BC6B15E4EFC0A00767E61109036D4D4D89F29.8611D5574969CBFE37CD52090FF9449BF47251CC&ratebypass=yes", "filesize": 1349417, "vcodec": "none", "format_note": "DASH audio", "abr": 70, "player_url": "//s.ytimg.com/yts/jsbin/player-en_US-vfl93P520/base.js", "ext": "webm", "preference": -50, "format_id": "250", "acodec": "opus"}, {"asr": 44100, "tbr": 127, "protocol": "https", "format": "171 - audio only (DASH audio)", "url": "https://r2---sn-uxax3vhgn-cxbr.googlevideo.com/videoplayback?id=0739f1c75d8fb65d&itag=171&source=youtube&requiressl=yes&gcr=rs&mm=31&ms=au&pl=17&mv=m&mn=sn-uxax3vhgn-cxbr&pcm2cms=yes&ratebypass=yes&mime=audio/webm&gir=yes&clen=2151689&lmt=1449553651508333&dur=148.452&signature=526355A8B530F30EE619FB8591C615F6C2C27975.0595C34D81B6D116C14A4069E73DC684A8550CEE&mt=1454902792&upn=tkOWzqnIelg&fexp=9415516,9416126,9418581,9419451,9420452,9422596,9422844,9422970,9423291,9423661,9423662,9425619,9426224,9426653,9427061,9427363,9427670&sver=3&key=dg_yt0&ip=109.92.0.167&ipbits=0&expire=1454924460&sparams=ip,ipbits,expire,id,itag,source,requiressl,gcr,mm,ms,pl,mv,mn,pcm2cms,ratebypass,mime,gir,clen,lmt,dur", "filesize": 2151689, "vcodec": "none", "format_note": "DASH audio", "abr": 128, "height": null, "width": null, "ext": "webm", "preference": -50, "fps": null, "format_id": "171", "http_headers": {"Accept-Charset": "ISO-8859-1,utf-8;q=0.7,*;q=0.7", "Accept-Language": "en-us,en;q=0.5", "Accept-Encoding": "gzip, deflate", "Accept": "text/html,application/xhtml+xml,application/xml;q=0.9,*/*;q=0.8", "User-Agent": "Mozilla/5.0 (X11; Linux x86_64; rv:10.0) Gecko/20150101 Firefox/20.0 (Chrome)"}, "acodec": "vorbis"}, {"asr": 44100, "tbr": 129, "container": "m4a_dash", "format": "140 - audio only (DASH audio)", "url": "https://r2---sn-uxax3vhgn-cxbr.googlevideo.com/videoplayback?id=0739f1c75d8fb65d&itag=140&source=youtube&requiressl=yes&gcr=rs&mm=31&ms=au&pl=17&mv=m&mn=sn-uxax3vhgn-cxbr&pcm2cms=yes&ratebypass=yes&mime=audio/mp4&gir=yes&clen=2384877&lmt=1429525671891325&dur=148.514&signature=19C6CC06F4E11A4D22D7555499A34D533DAD665C.15269ED158A50F38B39FC993BF1275E5582A2EA3&mt=1454902792&upn=tkOWzqnIelg&fexp=9415516,9416126,9418581,9419451,9420452,9422596,9422844,9422970,9423291,9423661,9423662,9425619,9426224,9426653,9427061,9427363,9427670&sver=3&key=dg_yt0&ip=109.92.0.167&ipbits=0&expire=1454924460&sparams=ip,ipbits,expire,id,itag,source,requiressl,gcr,mm,ms,pl,mv,mn,pcm2cms,ratebypass,mime,gir,clen,lmt,dur", "filesize": 2384877, "vcodec": "none", "format_note": "DASH audio", "ext": "m4a", "height": null, "width": null, "abr": 128, "preference": -50, "fps": null, "protocol": "https", "format_id": "140", "http_headers": {"Accept-Charset": "ISO-8859-1,utf-8;q=0.7,*;q=0.7", "Accept-Language": "en-us,en;q=0.5", "Accept-Encoding": "gzip, deflate", "Accept": "text/html,application/xhtml+xml,application/xml;q=0.9,*/*;q=0.8", "User-Agent": "Mozilla/5.0 (X11; Linux x86_64; rv:10.0) Gecko/20150101 Firefox/20.0 (Chrome)"}, "acodec": "mp4a.40.2"}, {"http_headers": {"Accept-Charset": "ISO-8859-1,utf-8;q=0.7,*;q=0.7", "Accept-Language": "en-us,en;q=0.5", "Accept-Encoding": "gzip, deflate", "Accept": "text/html,application/xhtml+xml,application/xml;q=0.9,*/*;q=0.8", "User-Agent": "Mozilla/5.0 (X11; Linux x86_64; rv:10.0) Gecko/20150101 Firefox/20.0 (Chrome)"}, "tbr": 150.929, "protocol": "https", "format": "251 - audio only (DASH audio)", "url": "https://r2---sn-uxax3vhgn-cxbr.googlevideo.com/videoplayback?itag=251&gcr=rs&source=youtube&clen=2610145&initcwndbps=1202500&upn=tkOWzqnIelg&expire=1454924460&sver=3&key=yt6&keepalive=yes&sparams=clen%2Cdur%2Cgcr%2Cgir%2Cid%2Cinitcwndbps%2Cip%2Cipbits%2Citag%2Ckeepalive%2Clmt%2Cmime%2Cmm%2Cmn%2Cms%2Cmv%2Cpcm2cms%2Cpl%2Crequiressl%2Csource%2Cupn%2Cexpire&mm=31&ip=109.92.0.167&mn=sn-uxax3vhgn-cxbr&ms=au&requiressl=yes&mt=1454902792&pl=17&mv=m&id=o-AFKb0GDhKsbyD5pke-0CCapkkZkMzXE_Ef8Jfu36_AS5&dur=148.461&mime=audio%2Fwebm&ipbits=0&pcm2cms=yes&gir=yes&fexp=9415516%2C9416126%2C9418581%2C9419451%2C9420452%2C9422596%2C9422844%2C9422970%2C9423291%2C9423661%2C9423662%2C9425619%2C9426224%2C9426653%2C9427061%2C9427363%2C9427670&lmt=1449553640166694&signature=3151A2CB39572CC1736ED83669503C5723BF1ABB.898EBE1E96C34D7EBFDC0DEAE9A167E550B8EC82&ratebypass=yes", "filesize": 2610145, "vcodec": "none", "format_note": "DASH audio", "abr": 160, "player_url": "//s.ytimg.com/yts/jsbin/player-en_US-vfl93P520/base.js", "ext": "webm", "preference": -50, "format_id": "251", "acodec": "opus"}, {"asr": 44100, "tbr": 255, "container": "m4a_dash", "format": "141 - audio only (DASH audio)", "url": "https://r2---sn-uxax3vhgn-cxbr.googlevideo.com/videoplayback?id=0739f1c75d8fb65d&itag=141&source=youtube&requiressl=yes&gcr=rs&mm=31&ms=au&pl=17&mv=m&mn=sn-uxax3vhgn-cxbr&pcm2cms=yes&ratebypass=yes&mime=audio/mp4&gir=yes&clen=4735590&lmt=1429525673336578&dur=148.514&signature=5EB1AF00449BA86B6E7ACA9C73C3D2F9069FBFFC.0FE62CF60B4AA3B5FF260463CF66D1BA8A11F711&mt=1454902792&upn=tkOWzqnIelg&fexp=9415516,9416126,9418581,9419451,9420452,9422596,9422844,9422970,9423291,9423661,9423662,9425619,9426224,9426653,9427061,9427363,9427670&sver=3&key=dg_yt0&ip=109.92.0.167&ipbits=0&expire=1454924460&sparams=ip,ipbits,expire,id,itag,source,requiressl,gcr,mm,ms,pl,mv,mn,pcm2cms,ratebypass,mime,gir,clen,lmt,dur", "filesize": 4735590, "vcodec": "none", "format_note": "DASH audio", "ext": "m4a", "height": null, "width": null, "abr": 256, "preference": -50, "fps": null, "protocol": "https", "format_id": "141", "http_headers": {"Accept-Charset": "ISO-8859-1,utf-8;q=0.7,*;q=0.7", "Accept-Language": "en-us,en;q=0.5", "Accept-Encoding": "gzip, deflate", "Accept": "text/html,application/xhtml+xml,application/xml;q=0.9,*/*;q=0.8", "User-Agent": "Mozilla/5.0 (X11; Linux x86_64; rv:10.0) Gecko/20150101 Firefox/20.0 (Chrome)"}, "acodec": "mp4a.40.2"}, {"asr": null, "tbr": 109, "protocol": "https", "format": "160 - 256x144 (DASH video)", "url": "https://r2---sn-uxax3vhgn-cxbr.googlevideo.com/videoplayback?id=0739f1c75d8fb65d&itag=160&source=youtube&requiressl=yes&gcr=rs&mm=31&ms=au&pl=17&mv=m&mn=sn-uxax3vhgn-cxbr&pcm2cms=yes&ratebypass=yes&mime=video/mp4&gir=yes&clen=1906702&lmt=1429525699614496&dur=148.500&signature=04FEB35B2B1486448A4C51262CDD505D322DBB35.6EAEA31AA34CE52D056EA65E7C5C9F50903C8DAB&mt=1454902792&upn=tkOWzqnIelg&fexp=9415516,9416126,9418581,9419451,9420452,9422596,9422844,9422970,9423291,9423661,9423662,9425619,9426224,9426653,9427061,9427363,9427670&sver=3&key=dg_yt0&ip=109.92.0.167&ipbits=0&expire=1454924460&sparams=ip,ipbits,expire,id,itag,source,requiressl,gcr,mm,ms,pl,mv,mn,pcm2cms,ratebypass,mime,gir,clen,lmt,dur", "vcodec": "avc1.4d400c", "format_note": "DASH video", "height": 144, "width": 256, "ext": "mp4", "preference": -40, "fps": 12, "format_id": "160", "acodec": "none", "http_headers": {"Accept-Charset": "ISO-8859-1,utf-8;q=0.7,*;q=0.7", "Accept-Language": "en-us,en;q=0.5", "Accept-Encoding": "gzip, deflate", "Accept": "text/html,application/xhtml+xml,application/xml;q=0.9,*/*;q=0.8", "User-Agent": "Mozilla/5.0 (X11; Linux x86_64; rv:10.0) Gecko/20150101 Firefox/20.0 (Chrome)"}, "filesize": 1906702}, {"asr": null, "tbr": 110, "container": "webm", "format": "278 - 256x144 (DASH video)", "url": "https://r2---sn-uxax3vhgn-cxbr.googlevideo.com/videoplayback?id=0739f1c75d8fb65d&itag=278&source=youtube&requiressl=yes&gcr=rs&mm=31&ms=au&pl=17&mv=m&mn=sn-uxax3vhgn-cxbr&pcm2cms=yes&ratebypass=yes&mime=video/webm&gir=yes&clen=1546631&lmt=1449553959123412&dur=148.417&signature=13F71C358FC9F5BD12DFD6B2BC662B74C59FD937.21F38957E0910194B738E4E58017D7DA8CA37B75&mt=1454902792&upn=tkOWzqnIelg&fexp=9415516,9416126,9418581,9419451,9420452,9422596,9422844,9422970,9423291,9423661,9423662,9425619,9426224,9426653,9427061,9427363,9427670&sver=3&key=dg_yt0&ip=109.92.0.167&ipbits=0&expire=1454924460&sparams=ip,ipbits,expire,id,itag,source,requiressl,gcr,mm,ms,pl,mv,mn,pcm2cms,ratebypass,mime,gir,clen,lmt,dur", "vcodec": "vp9", "format_note": "DASH video", "height": 144, "width": 256, "ext": "webm", "preference": -40, "fps": 12, "protocol": "https", "format_id": "278", "acodec": "none", "http_headers": {"Accept-Charset": "ISO-8859-1,utf-8;q=0.7,*;q=0.7", "Accept-Language": "en-us,en;q=0.5", "Accept-Encoding": "gzip, deflate", "Accept": "text/html,application/xhtml+xml,application/xml;q=0.9,*/*;q=0.8", "User-Agent": "Mozilla/5.0 (X11; Linux x86_64; rv:10.0) Gecko/20150101 Firefox/20.0 (Chrome)"}, "filesize": 1546631}, {"asr": null, "tbr": 249, "protocol": "https", "format": "133 - 426x240 (DASH video)", "url": "https://r2---sn-uxax3vhgn-cxbr.googlevideo.com/videoplayback?id=0739f1c75d8fb65d&itag=133&source=youtube&requiressl=yes&gcr=rs&mm=31&ms=au&pl=17&mv=m&mn=sn-uxax3vhgn-cxbr&pcm2cms=yes&ratebypass=yes&mime=video/mp4&gir=yes&clen=4342714&lmt=1429525710577134&dur=148.458&signature=70418B6CC6B5C987DFB1630FB50E3CF7EC599E4D.4BB08290C2D9849DEE0BC8DFBC2759277A2B7AF4&mt=1454902792&upn=tkOWzqnIelg&fexp=9415516,9416126,9418581,9419451,9420452,9422596,9422844,9422970,9423291,9423661,9423662,9425619,9426224,9426653,9427061,9427363,9427670&sver=3&key=dg_yt0&ip=109.92.0.167&ipbits=0&expire=1454924460&sparams=ip,ipbits,expire,id,itag,source,requiressl,gcr,mm,ms,pl,mv,mn,pcm2cms,ratebypass,mime,gir,clen,lmt,dur", "vcodec": "avc1.4d4015", "format_note": "DASH video", "height": 240, "width": 426, "ext": "mp4", "preference": -40, "fps": 24, "format_id": "133", "acodec": "none", "http_headers": {"Accept-Charset": "ISO-8859-1,utf-8;q=0.7,*;q=0.7", "Accept-Language": "en-us,en;q=0.5", "Accept-Encoding": "gzip, deflate", "Accept": "text/html,application/xhtml+xml,application/xml;q=0.9,*/*;q=0.8", "User-Agent": "Mozilla/5.0 (X11; Linux x86_64; rv:10.0) Gecko/20150101 Firefox/20.0 (Chrome)"}, "filesize": 4342714}, {"asr": null, "tbr": 254, "protocol": "https", "format": "242 - 426x240 (DASH video)", "url": "https://r2---sn-uxax3vhgn-cxbr.googlevideo.com/videoplayback?id=0739f1c75d8fb65d&itag=242&source=youtube&requiressl=yes&gcr=rs&mm=31&ms=au&pl=17&mv=m&mn=sn-uxax3vhgn-cxbr&pcm2cms=yes&ratebypass=yes&mime=video/webm&gir=yes&clen=3503345&lmt=1449553961796370&dur=148.417&signature=0FEA8D7F26B8E011D330CD912D479D3DA3AE24BE.1E50877E72A63243B5E5DCF1522B61336244BF13&mt=1454902792&upn=tkOWzqnIelg&fexp=9415516,9416126,9418581,9419451,9420452,9422596,9422844,9422970,9423291,9423661,9423662,9425619,9426224,9426653,9427061,9427363,9427670&sver=3&key=dg_yt0&ip=109.92.0.167&ipbits=0&expire=1454924460&sparams=ip,ipbits,expire,id,itag,source,requiressl,gcr,mm,ms,pl,mv,mn,pcm2cms,ratebypass,mime,gir,clen,lmt,dur", "vcodec": "vp9", "format_note": "DASH video", "height": 240, "width": 426, "ext": "webm", "preference": -40, "fps": 24, "format_id": "242", "acodec": "none", "http_headers": {"Accept-Charset": "ISO-8859-1,utf-8;q=0.7,*;q=0.7", "Accept-Language": "en-us,en;q=0.5", "Accept-Encoding": "gzip, deflate", "Accept": "text/html,application/xhtml+xml,application/xml;q=0.9,*/*;q=0.8", "User-Agent": "Mozilla/5.0 (X11; Linux x86_64; rv:10.0) Gecko/20150101 Firefox/20.0 (Chrome)"}, "filesize": 3503345}, {"asr": null, "tbr": 462, "protocol": "https", "format": "243 - 640x360 (DASH video)", "url": "https://r2---sn-uxax3vhgn-cxbr.googlevideo.com/videoplayback?id=0739f1c75d8fb65d&itag=243&source=youtube&requiressl=yes&gcr=rs&mm=31&ms=au&pl=17&mv=m&mn=sn-uxax3vhgn-cxbr&pcm2cms=yes&ratebypass=yes&mime=video/webm&gir=yes&clen=6384022&lmt=1449553961114690&dur=148.417&signature=7A492B6D6B4C4F2106A0E6964A3B183F2EBEAEB6.196EA4A8688A217EA4D27E2540AA6018033FE755&mt=1454902792&upn=tkOWzqnIelg&fexp=9415516,9416126,9418581,9419451,9420452,9422596,9422844,9422970,9423291,9423661,9423662,9425619,9426224,9426653,9427061,9427363,9427670&sver=3&key=dg_yt0&ip=109.92.0.167&ipbits=0&expire=1454924460&sparams=ip,ipbits,expire,id,itag,source,requiressl,gcr,mm,ms,pl,mv,mn,pcm2cms,ratebypass,mime,gir,clen,lmt,dur", "vcodec": "vp9", "format_note": "DASH video", "height": 360, "width": 640, "ext": "webm", "preference": -40, "fps": 24, "format_id": "243", "acodec": "none", "http_headers": {"Accept-Charset": "ISO-8859-1,utf-8;q=0.7,*;q=0.7", "Accept-Language": "en-us,en;q=0.5", "Accept-Encoding": "gzip, deflate", "Accept": "text/html,application/xhtml+xml,application/xml;q=0.9,*/*;q=0.8", "User-Agent": "Mozilla/5.0 (X11; Linux x86_64; rv:10.0) Gecko/20150101 Firefox/20.0 (Chrome)"}, "filesize": 6384022}, {"asr": null, "tbr": 608, "protocol": "https", "format": "134 - 640x360 (DASH video)", "url": "https://r2---sn-uxax3vhgn-cxbr.googlevideo.com/videoplayback?id=0739f1c75d8fb65d&itag=134&source=youtube&requiressl=yes&gcr=rs&mm=31&ms=au&pl=17&mv=m&mn=sn-uxax3vhgn-cxbr&pcm2cms=yes&ratebypass=yes&mime=video/mp4&gir=yes&clen=8073981&lmt=1429525736523641&dur=148.458&signature=519A861EA517021148DECC1F324D7325905E06E0.4B16B3A85ECE2BD67B6C43A2B81ED0D56EEFCE69&mt=1454902792&upn=tkOWzqnIelg&fexp=9415516,9416126,9418581,9419451,9420452,9422596,9422844,9422970,9423291,9423661,9423662,9425619,9426224,9426653,9427061,9427363,9427670&sver=3&key=dg_yt0&ip=109.92.0.167&ipbits=0&expire=1454924460&sparams=ip,ipbits,expire,id,itag,source,requiressl,gcr,mm,ms,pl,mv,mn,pcm2cms,ratebypass,mime,gir,clen,lmt,dur", "vcodec": "avc1.4d401e", "format_note": "DASH video", "height": 360, "width": 640, "ext": "mp4", "preference": -40, "fps": 24, "format_id": "134", "acodec": "none", "http_headers": {"Accept-Charset": "ISO-8859-1,utf-8;q=0.7,*;q=0.7", "Accept-Language": "en-us,en;q=0.5", "Accept-Encoding": "gzip, deflate", "Accept": "text/html,application/xhtml+xml,application/xml;q=0.9,*/*;q=0.8", "User-Agent": "Mozilla/5.0 (X11; Linux x86_64; rv:10.0) Gecko/20150101 Firefox/20.0 (Chrome)"}, "filesize": 8073981}, {"asr": null, "tbr": 827, "protocol": "https", "format": "244 - 854x480 (DASH video)", "url": "https://r2---sn-uxax3vhgn-cxbr.googlevideo.com/videoplayback?id=0739f1c75d8fb65d&itag=244&source=youtube&requiressl=yes&gcr=rs&mm=31&ms=au&pl=17&mv=m&mn=sn-uxax3vhgn-cxbr&pcm2cms=yes&ratebypass=yes&mime=video/webm&gir=yes&clen=11350548&lmt=1449553964291812&dur=148.417&signature=1BB7B7C23A8E02401590DCCD7B829F96DA291132.3C0928F39B0598F6DF660AF490E056D1DE7140C0&mt=1454902792&upn=tkOWzqnIelg&fexp=9415516,9416126,9418581,9419451,9420452,9422596,9422844,9422970,9423291,9423661,9423662,9425619,9426224,9426653,9427061,9427363,9427670&sver=3&key=dg_yt0&ip=109.92.0.167&ipbits=0&expire=1454924460&sparams=ip,ipbits,expire,id,itag,source,requiressl,gcr,mm,ms,pl,mv,mn,pcm2cms,ratebypass,mime,gir,clen,lmt,dur", "vcodec": "vp9", "format_note": "DASH video", "height": 480, "width": 854, "ext": "webm", "preference": -40, "fps": 24, "format_id": "244", "acodec": "none", "http_headers": {"Accept-Charset": "ISO-8859-1,utf-8;q=0.7,*;q=0.7", "Accept-Language": "en-us,en;q=0.5", "Accept-Encoding": "gzip, deflate", "Accept": "text/html,application/xhtml+xml,application/xml;q=0.9,*/*;q=0.8", "User-Agent": "Mozilla/5.0 (X11; Linux x86_64; rv:10.0) Gecko/20150101 Firefox/20.0 (Chrome)"}, "filesize": 11350548}, {"asr": null, "tbr": 1116, "protocol": "https", "format": "135 - 854x480 (DASH video)", "url": "https://r2---sn-uxax3vhgn-cxbr.googlevideo.com/videoplayback?id=0739f1c75d8fb65d&itag=135&source=youtube&requiressl=yes&gcr=rs&mm=31&ms=au&pl=17&mv=m&mn=sn-uxax3vhgn-cxbr&pcm2cms=yes&ratebypass=yes&mime=video/mp4&gir=yes&clen=14987417&lmt=1429525716394175&dur=148.458&signature=5CDB4AC5726523D2235B46E5D9CEC6F5EE998605.9345B9099C33C1C20235ED2DD0271A97660405B9&mt=1454902792&upn=tkOWzqnIelg&fexp=9415516,9416126,9418581,9419451,9420452,9422596,9422844,9422970,9423291,9423661,9423662,9425619,9426224,9426653,9427061,9427363,9427670&sver=3&key=dg_yt0&ip=109.92.0.167&ipbits=0&expire=1454924460&sparams=ip,ipbits,expire,id,itag,source,requiressl,gcr,mm,ms,pl,mv,mn,pcm2cms,ratebypass,mime,gir,clen,lmt,dur", "vcodec": "avc1.4d401e", "format_note": "DASH video", "height": 480, "width": 854, "ext": "mp4", "preference": -40, "fps": 24, "format_id": "135", "acodec": "none", "http_headers": {"Accept-Charset": "ISO-8859-1,utf-8;q=0.7,*;q=0.7", "Accept-Language": "en-us,en;q=0.5", "Accept-Encoding": "gzip, deflate", "Accept": "text/html,application/xhtml+xml,application/xml;q=0.9,*/*;q=0.8", "User-Agent": "Mozilla/5.0 (X11; Linux x86_64; rv:10.0) Gecko/20150101 Firefox/20.0 (Chrome)"}, "filesize": 14987417}, {"asr": null, "tbr": 1596, "protocol": "https", "format": "247 - 1280x720 (DASH video)", "url": "https://r2---sn-uxax3vhgn-cxbr.googlevideo.com/videoplayback?id=0739f1c75d8fb65d&itag=247&source=youtube&requiressl=yes&gcr=rs&mm=31&ms=au&pl=17&mv=m&mn=sn-uxax3vhgn-cxbr&pcm2cms=yes&ratebypass=yes&mime=video/webm&gir=yes&clen=21677842&lmt=1449553960973950&dur=148.417&signature=4585169410B2ECB3A9FE4EFCB8C7C600A6FCDC7B.7576DA03DFE930F951271D8782E8C94FF782E62C&mt=1454902792&upn=tkOWzqnIelg&fexp=9415516,9416126,9418581,9419451,9420452,9422596,9422844,9422970,9423291,9423661,9423662,9425619,9426224,9426653,9427061,9427363,9427670&sver=3&key=dg_yt0&ip=109.92.0.167&ipbits=0&expire=1454924460&sparams=ip,ipbits,expire,id,itag,source,requiressl,gcr,mm,ms,pl,mv,mn,pcm2cms,ratebypass,mime,gir,clen,lmt,dur", "vcodec": "vp9", "format_note": "DASH video", "height": 720, "width": 1280, "ext": "webm", "preference": -40, "fps": 24, "format_id": "247", "acodec": "none", "http_headers": {"Accept-Charset": "ISO-8859-1,utf-8;q=0.7,*;q=0.7", "Accept-Language": "en-us,en;q=0.5", "Accept-Encoding": "gzip, deflate", "Accept": "text/html,application/xhtml+xml,application/xml;q=0.9,*/*;q=0.8", "User-Agent": "Mozilla/5.0 (X11; Linux x86_64; rv:10.0) Gecko/20150101 Firefox/20.0 (Chrome)"}, "filesize": 21677842}, {"asr": null, "tbr": 2225, "protocol": "https", "format": "136 - 1280x720 (DASH video)", "url": "https://r2---sn-uxax3vhgn-cxbr.googlevideo.com/videoplayback?id=0739f1c75d8fb65d&itag=136&source=youtube&requiressl=yes&gcr=rs&mm=31&ms=au&pl=17&mv=m&mn=sn-uxax3vhgn-cxbr&pcm2cms=yes&ratebypass=yes&mime=video/mp4&gir=yes&clen=27391291&lmt=1429525792828724&dur=148.458&signature=0C2158657C8A6257967E7AAD4ED573B6FF14E499.57EC62035B428331919DAA36E0CFDA00AF95F59D&mt=1454902792&upn=tkOWzqnIelg&fexp=9415516,9416126,9418581,9419451,9420452,9422596,9422844,9422970,9423291,9423661,9423662,9425619,9426224,9426653,9427061,9427363,9427670&sver=3&key=dg_yt0&ip=109.92.0.167&ipbits=0&expire=1454924460&sparams=ip,ipbits,expire,id,itag,source,requiressl,gcr,mm,ms,pl,mv,mn,pcm2cms,ratebypass,mime,gir,clen,lmt,dur", "vcodec": "avc1.4d401f", "format_note": "DASH video", "height": 720, "width": 1280, "ext": "mp4", "preference": -40, "fps": 24, "format_id": "136", "acodec": "none", "http_headers": {"Accept-Charset": "ISO-8859-1,utf-8;q=0.7,*;q=0.7", "Accept-Language": "en-us,en;q=0.5", "Accept-Encoding": "gzip, deflate", "Accept": "text/html,application/xhtml+xml,application/xml;q=0.9,*/*;q=0.8", "User-Agent": "Mozilla/5.0 (X11; Linux x86_64; rv:10.0) Gecko/20150101 Firefox/20.0 (Chrome)"}, "filesize": 27391291}, {"asr": null, "tbr": 2837, "protocol": "https", "format": "248 - 1920x1080 (DASH video)", "url": "https://r2---sn-uxax3vhgn-cxbr.googlevideo.com/videoplayback?id=0739f1c75d8fb65d&itag=248&source=youtube&requiressl=yes&gcr=rs&mm=31&ms=au&pl=17&mv=m&mn=sn-uxax3vhgn-cxbr&pcm2cms=yes&ratebypass=yes&mime=video/webm&gir=yes&clen=37720699&lmt=1449553863267095&dur=148.417&signature=6426A5C22177D2A3DFEE2ADEF20DD113344FF8FB.28361E48F48AC23F7F003CEE4D11C1C82F968772&mt=1454902792&upn=tkOWzqnIelg&fexp=9415516,9416126,9418581,9419451,9420452,9422596,9422844,9422970,9423291,9423661,9423662,9425619,9426224,9426653,9427061,9427363,9427670&sver=3&key=dg_yt0&ip=109.92.0.167&ipbits=0&expire=1454924460&sparams=ip,ipbits,expire,id,itag,source,requiressl,gcr,mm,ms,pl,mv,mn,pcm2cms,ratebypass,mime,gir,clen,lmt,dur", "vcodec": "vp9", "format_note": "DASH video", "height": 1080, "width": 1920, "ext": "webm", "preference": -40, "fps": 24, "format_id": "248", "acodec": "none", "http_headers": {"Accept-Charset": "ISO-8859-1,utf-8;q=0.7,*;q=0.7", "Accept-Language": "en-us,en;q=0.5", "Accept-Encoding": "gzip, deflate", "Accept": "text/html,application/xhtml+xml,application/xml;q=0.9,*/*;q=0.8", "User-Agent": "Mozilla/5.0 (X11; Linux x86_64; rv:10.0) Gecko/20150101 Firefox/20.0 (Chrome)"}, "filesize": 37720699}, {"asr": null, "tbr": 4084, "protocol": "https", "format": "137 - 1920x1080 (DASH video)", "url": "https://r2---sn-uxax3vhgn-cxbr.googlevideo.com/videoplayback?id=0739f1c75d8fb65d&itag=137&source=youtube&requiressl=yes&gcr=rs&mm=31&ms=au&pl=17&mv=m&mn=sn-uxax3vhgn-cxbr&pcm2cms=yes&ratebypass=yes&mime=video/mp4&gir=yes&clen=47163660&lmt=1429525838593278&dur=148.458&signature=8EC45E8334E9F7E676F504F04E61B75AD4DD32EE.7BD3BCFF95F02165CCB40B96931B535061BABA9B&mt=1454902792&upn=tkOWzqnIelg&fexp=9415516,9416126,9418581,9419451,9420452,9422596,9422844,9422970,9423291,9423661,9423662,9425619,9426224,9426653,9427061,9427363,9427670&sver=3&key=dg_yt0&ip=109.92.0.167&ipbits=0&expire=1454924460&sparams=ip,ipbits,expire,id,itag,source,requiressl,gcr,mm,ms,pl,mv,mn,pcm2cms,ratebypass,mime,gir,clen,lmt,dur", "vcodec": "avc1.640028", "format_note": "DASH video", "height": 1080, "width": 1920, "ext": "mp4", "preference": -40, "fps": 24, "format_id": "137", "acodec": "none", "http_headers": {"Accept-Charset": "ISO-8859-1,utf-8;q=0.7,*;q=0.7", "Accept-Language": "en-us,en;q=0.5", "Accept-Encoding": "gzip, deflate", "Accept": "text/html,application/xhtml+xml,application/xml;q=0.9,*/*;q=0.8", "User-Agent": "Mozilla/5.0 (X11; Linux x86_64; rv:10.0) Gecko/20150101 Firefox/20.0 (Chrome)"}, "filesize": 47163660}, {"http_headers": {"Accept-Charset": "ISO-8859-1,utf-8;q=0.7,*;q=0.7", "Accept-Language": "en-us,en;q=0.5", "Accept-Encoding": "gzip, deflate", "Accept": "text/html,application/xhtml+xml,application/xml;q=0.9,*/*;q=0.8", "User-Agent": "Mozilla/5.0 (X11; Linux x86_64; rv:10.0) Gecko/20150101 Firefox/20.0 (Chrome)"}, "protocol": "https", "format": "17 - 176x144 (small)", "url": "https://r2---sn-uxax3vhgn-cxbr.googlevideo.com/videoplayback?itag=17&gcr=rs&source=youtube&upn=tkOWzqnIelg&initcwndbps=1202500&expire=1454924460&sver=3&key=yt6&sparams=dur%2Cgcr%2Cid%2Cinitcwndbps%2Cip%2Cipbits%2Citag%2Clmt%2Cmime%2Cmm%2Cmn%2Cms%2Cmv%2Cpcm2cms%2Cpl%2Crequiressl%2Csource%2Cupn%2Cexpire&mm=31&ip=109.92.0.167&mn=sn-uxax3vhgn-cxbr&ms=au&requiressl=yes&mt=1454902792&pl=17&mv=m&id=o-AFKb0GDhKsbyD5pke-0CCapkkZkMzXE_Ef8Jfu36_AS5&dur=148.654&mime=video%2F3gpp&ipbits=0&pcm2cms=yes&fexp=9415516%2C9416126%2C9418581%2C9419451%2C9420452%2C9422596%2C9422844%2C9422970%2C9423291%2C9423661%2C9423662%2C9425619%2C9426224%2C9426653%2C9427061%2C9427363%2C9427670&lmt=1412343884172088&signature=42D5E345C72D6D5A184F707CBE654E6514131A7C.833548E86E370301A27E436C177E9DDB5722B883&ratebypass=yes", "vcodec": "mp4v.20.3", "format_note": "small", "ext": "3gp", "player_url": "//s.ytimg.com/yts/jsbin/player-en_US-vfl93P520/base.js", "width": 176, "abr": 24, "format_id": "17", "height": 144, "acodec": " mp4a.40.2"}, {"http_headers": {"Accept-Charset": "ISO-8859-1,utf-8;q=0.7,*;q=0.7", "Accept-Language": "en-us,en;q=0.5", "Accept-Encoding": "gzip, deflate", "Accept": "text/html,application/xhtml+xml,application/xml;q=0.9,*/*;q=0.8", "User-Agent": "Mozilla/5.0 (X11; Linux x86_64; rv:10.0) Gecko/20150101 Firefox/20.0 (Chrome)"}, "protocol": "https", "format": "36 - 320x240 (small)", "url": "https://r2---sn-uxax3vhgn-cxbr.googlevideo.com/videoplayback?itag=36&gcr=rs&source=youtube&upn=tkOWzqnIelg&initcwndbps=1202500&expire=1454924460&sver=3&key=yt6&sparams=dur%2Cgcr%2Cid%2Cinitcwndbps%2Cip%2Cipbits%2Citag%2Clmt%2Cmime%2Cmm%2Cmn%2Cms%2Cmv%2Cpcm2cms%2Cpl%2Crequiressl%2Csource%2Cupn%2Cexpire&mm=31&ip=109.92.0.167&mn=sn-uxax3vhgn-cxbr&ms=au&requiressl=yes&mt=1454902792&pl=17&mv=m&id=o-AFKb0GDhKsbyD5pke-0CCapkkZkMzXE_Ef8Jfu36_AS5&dur=148.654&mime=video%2F3gpp&ipbits=0&pcm2cms=yes&fexp=9415516%2C9416126%2C9418581%2C9419451%2C9420452%2C9422596%2C9422844%2C9422970%2C9423291%2C9423661%2C9423662%2C9425619%2C9426224%2C9426653%2C9427061%2C9427363%2C9427670&lmt=1412343890368960&signature=AECC6C19614313930AC357F62089D8284D344EBD.9D2937B5CC314410A1957FD5886670EC799FD4A5&ratebypass=yes", "vcodec": "mp4v.20.3", "format_note": "small", "ext": "3gp", "player_url": "//s.ytimg.com/yts/jsbin/player-en_US-vfl93P520/base.js", "width": 320, "abr": 32, "format_id": "36", "height": 240, "acodec": " mp4a.40.2"}, {"http_headers": {"Accept-Charset": "ISO-8859-1,utf-8;q=0.7,*;q=0.7", "Accept-Language": "en-us,en;q=0.5", "Accept-Encoding": "gzip, deflate", "Accept": "text/html,application/xhtml+xml,application/xml;q=0.9,*/*;q=0.8", "User-Agent": "Mozilla/5.0 (X11; Linux x86_64; rv:10.0) Gecko/20150101 Firefox/20.0 (Chrome)"}, "protocol": "https", "format": "5 - 400x240 (small)", "url": "https://r2---sn-uxax3vhgn-cxbr.googlevideo.com/videoplayback?itag=5&gcr=rs&source=youtube&upn=tkOWzqnIelg&initcwndbps=1202500&expire=1454924460&sver=3&key=yt6&sparams=dur%2Cgcr%2Cid%2Cinitcwndbps%2Cip%2Cipbits%2Citag%2Clmt%2Cmime%2Cmm%2Cmn%2Cms%2Cmv%2Cpcm2cms%2Cpl%2Crequiressl%2Csource%2Cupn%2Cexpire&mm=31&ip=109.92.0.167&mn=sn-uxax3vhgn-cxbr&ms=au&requiressl=yes&mt=1454902792&pl=17&mv=m&id=o-AFKb0GDhKsbyD5pke-0CCapkkZkMzXE_Ef8Jfu36_AS5&dur=148.506&mime=video%2Fx-flv&ipbits=0&pcm2cms=yes&fexp=9415516%2C9416126%2C9418581%2C9419451%2C9420452%2C9422596%2C9422844%2C9422970%2C9423291%2C9423661%2C9423662%2C9425619%2C9426224%2C9426653%2C9427061%2C9427363%2C9427670&lmt=1412343861716008&signature=303411C40452C03FAA5D9BBF941AEF041588F3B2.40231C9B15FFC217525762EB643D6B4168AC475E&ratebypass=yes", "vcodec": "h263", "format_note": "small", "ext": "flv", "player_url": "//s.ytimg.com/yts/jsbin/player-en_US-vfl93P520/base.js", "width": 400, "abr": 64, "format_id": "5", "height": 240, "acodec": "mp3"}, {"http_headers": {"Accept-Charset": "ISO-8859-1,utf-8;q=0.7,*;q=0.7", "Accept-Language": "en-us,en;q=0.5", "Accept-Encoding": "gzip, deflate", "Accept": "text/html,application/xhtml+xml,application/xml;q=0.9,*/*;q=0.8", "User-Agent": "Mozilla/5.0 (X11; Linux x86_64; rv:10.0) Gecko/20150101 Firefox/20.0 (Chrome)"}, "protocol": "https", "format": "43 - 640x360 (medium)", "url": "https://r2---sn-uxax3vhgn-cxbr.googlevideo.com/videoplayback?itag=43&gcr=rs&source=youtube&ratebypass=yes&upn=tkOWzqnIelg&initcwndbps=1202500&expire=1454924460&sver=3&key=yt6&sparams=dur%2Cgcr%2Cid%2Cinitcwndbps%2Cip%2Cipbits%2Citag%2Clmt%2Cmime%2Cmm%2Cmn%2Cms%2Cmv%2Cpcm2cms%2Cpl%2Cratebypass%2Crequiressl%2Csource%2Cupn%2Cexpire&mm=31&ip=109.92.0.167&mn=sn-uxax3vhgn-cxbr&ms=au&requiressl=yes&mt=1454902792&pl=17&mv=m&id=o-AFKb0GDhKsbyD5pke-0CCapkkZkMzXE_Ef8Jfu36_AS5&dur=0.000&mime=video%2Fwebm&ipbits=0&pcm2cms=yes&fexp=9415516%2C9416126%2C9418581%2C9419451%2C9420452%2C9422596%2C9422844%2C9422970%2C9423291%2C9423661%2C9423662%2C9425619%2C9426224%2C9426653%2C9427061%2C9427363%2C9427670&lmt=1412346762636620&signature=C111C5B75D0D051BD08CC0F70CD6024387CCBA3C.0C573F08C50FFB02759887392F1F5B8AEBECD86E", "vcodec": "vp8.0", "format_note": "medium", "ext": "webm", "player_url": "//s.ytimg.com/yts/jsbin/player-en_US-vfl93P520/base.js", "width": 640, "abr": 128, "format_id": "43", "height": 360, "acodec": " vorbis"}, {"http_headers": {"Accept-Charset": "ISO-8859-1,utf-8;q=0.7,*;q=0.7", "Accept-Language": "en-us,en;q=0.5", "Accept-Encoding": "gzip, deflate", "Accept": "text/html,application/xhtml+xml,application/xml;q=0.9,*/*;q=0.8", "User-Agent": "Mozilla/5.0 (X11; Linux x86_64; rv:10.0) Gecko/20150101 Firefox/20.0 (Chrome)"}, "protocol": "https", "format": "18 - 640x360 (medium)", "url": "https://r2---sn-uxax3vhgn-cxbr.googlevideo.com/videoplayback?itag=18&gcr=rs&source=youtube&ratebypass=yes&upn=tkOWzqnIelg&initcwndbps=1202500&expire=1454924460&sver=3&key=yt6&sparams=dur%2Cgcr%2Cid%2Cinitcwndbps%2Cip%2Cipbits%2Citag%2Clmt%2Cmime%2Cmm%2Cmn%2Cms%2Cmv%2Cpcm2cms%2Cpl%2Cratebypass%2Crequiressl%2Csource%2Cupn%2Cexpire&mm=31&ip=109.92.0.167&mn=sn-uxax3vhgn-cxbr&ms=au&requiressl=yes&mt=1454902792&pl=17&mv=m&id=o-AFKb0GDhKsbyD5pke-0CCapkkZkMzXE_Ef8Jfu36_AS5&dur=148.514&mime=video%2Fmp4&ipbits=0&pcm2cms=yes&fexp=9415516%2C9416126%2C9418581%2C9419451%2C9420452%2C9422596%2C9422844%2C9422970%2C9423291%2C9423661%2C9423662%2C9425619%2C9426224%2C9426653%2C9427061%2C9427363%2C9427670&lmt=1429525739060861&signature=8D5AD50DE5CA253F86A44952D100F3C11BEF84A8.85812400F0190D9DB2746A6C69441B0B0CB109A1", "vcodec": "avc1.42001E", "format_note": "medium", "ext": "mp4", "player_url": "//s.ytimg.com/yts/jsbin/player-en_US-vfl93P520/base.js", "width": 640, "abr": 96, "format_id": "18", "height": 360, "acodec": " mp4a.40.2"}, {"http_headers": {"Accept-Charset": "ISO-8859-1,utf-8;q=0.7,*;q=0.7", "Accept-Language": "en-us,en;q=0.5", "Accept-Encoding": "gzip, deflate", "Accept": "text/html,application/xhtml+xml,application/xml;q=0.9,*/*;q=0.8", "User-Agent": "Mozilla/5.0 (X11; Linux x86_64; rv:10.0) Gecko/20150101 Firefox/20.0 (Chrome)"}, "protocol": "https", "format": "22 - 1280x720 (hd720)", "url": "https://r2---sn-uxax3vhgn-cxbr.googlevideo.com/videoplayback?itag=22&gcr=rs&source=youtube&ratebypass=yes&upn=tkOWzqnIelg&initcwndbps=1202500&expire=1454924460&sver=3&key=yt6&sparams=dur%2Cgcr%2Cid%2Cinitcwndbps%2Cip%2Cipbits%2Citag%2Clmt%2Cmime%2Cmm%2Cmn%2Cms%2Cmv%2Cpcm2cms%2Cpl%2Cratebypass%2Crequiressl%2Csource%2Cupn%2Cexpire&mm=31&ip=109.92.0.167&mn=sn-uxax3vhgn-cxbr&ms=au&requiressl=yes&mt=1454902792&pl=17&mv=m&id=o-AFKb0GDhKsbyD5pke-0CCapkkZkMzXE_Ef8Jfu36_AS5&dur=148.514&mime=video%2Fmp4&ipbits=0&pcm2cms=yes&fexp=9415516%2C9416126%2C9418581%2C9419451%2C9420452%2C9422596%2C9422844%2C9422970%2C9423291%2C9423661%2C9423662%2C9425619%2C9426224%2C9426653%2C9427061%2C9427363%2C9427670&lmt=1429525764283120&signature=B2E05B810A33FBD8A43062ED33B37E05F2907F14.3D30E84B8F134E02C4C9504582CAFC8945F2D024", "vcodec": "avc1.64001F", "format_note": "hd720", "ext": "mp4", "player_url": "//s.ytimg.com/yts/jsbin/player-en_US-vfl93P520/base.js", "width": 1280, "abr": 192, "format_id": "22", "height": 720, "acodec": " mp4a.40.2"}], "width": 1280}